support_sbk/__init__.py
support_sbk/__main__.py
support_sbk/cli.py
support_sbk-2.2.1.dist-info/METADATA
support_sbk-2.2.1.dist-info/WHEEL
support_sbk-2.2.1.dist-info/entry_points.txt
support_sbk-2.2.1.dist-info/top_level.txt
support_sbk-2.2.1.dist-info/RECORD
